CONTRIBUTORS
LICENSE
MANIFEST.in
README.rst
setup.py
django_ifgy_login.egg-info/PKG-INFO
django_ifgy_login.egg-info/SOURCES.txt
django_ifgy_login.egg-info/dependency_links.txt
django_ifgy_login.egg-info/top_level.txt
ifgy_login/__init__.py
ifgy_login/models.py
ifgy_login/settings.py
ifgy_login/tests.py
ifgy_login/urls.py
ifgy_login/views.py
ifgy_login/templates/login.html