Metadata-Version: 1.1
Name: django-ifgy-login
Version: 0.3
Summary: A simple Django app to conduct login/logout.
Home-page: https://github.com/Infranology
Author: Rodrigo Prior Bechelli
Author-email: rprior@infranology.com.br
License: BSD License
Platform: UNKNOWN
Classifier: Environment :: Web Environment
Classifier: Framework :: Django
Classifier: Intended Audience :: Developers
Classifier: License :: OSI Approved :: BSD License
Classifier: Operating System :: OS Independent
Classifier: Programming Language :: Python
Classifier: Programming Language :: Python :: 2.6
Classifier: Programming Language :: Python :: 2.7
Classifier: Topic :: Internet :: WWW/HTTP
Classifier: Topic :: Internet :: WWW/HTTP :: Dynamic Content
